tofa/__init__.py
tofa/_typing.py
tofa/bbox_utils.py
tofa/cache.py
tofa/checkpoints.py
tofa/colors.py
tofa/config.py
tofa/filesystem.py
tofa/image_transforms.py
tofa/io.py
tofa/logging.py
tofa/loss.py
tofa/meters.py
tofa/misc.py
tofa/registry.py
tofa/reproducibility.py
tofa/schedulers.py
tofa/timers.py
tofa/torch_utils.py
tofa/transforms.py
tofa/visualization.py
tofa-0.0.10.dist-info/LICENSE
tofa-0.0.10.dist-info/METADATA
tofa-0.0.10.dist-info/WHEEL
tofa-0.0.10.dist-info/RECORD
